[{"name":"Alabama","candy":{"seventies":{"hershey":"28.57","mars":"14.65","lindt":"24.54","nestle":"27.47","other":"4.76"},"eighties":{"hershey":"15.92","mars":"46.27","lindt":"20.90","nestle":"7.46","other":"9.45"},"ninties":{"hershey":"30.74","mars":"22.96","lindt":"14.44","nestle":"27.04","other":"4.81"},"oughts":{"hershey":"43.29","mars":"15.24","lindt":"39.63","nestle":"1.22","other":"0.61"}}},{"name":"Alaska","candy":{"seventies":{"hershey":"30.94","mars":"11.66","lindt":"31.84","nestle":"11.66","other":"13.90"},"eighties":{"hershey":"42.02","mars":"18.91","lindt":"22.27","nestle":"12.18","other":"4.62"},"ninties":{"hershey":"24.35","mars":"29.22","lindt":"31.82","nestle":"12.66","other":"1.95"},"oughts":{"hershey":"31.82","mars":"44.44","lindt":"2.02","nestle":"13.13","other":"8.59"}}},{"name":"Arizona","candy":{"seventies":{"hershey":"15.98","mars":"37.44","lindt":"26.03","nestle":"15.07","other":"5.48"},"eighties":{"hershey":"19.76","mars":"29.79","lindt":"15.81","nestle":"27.66","other":"6.99"},"ninties":{"hershey":"35.02","mars":"2.76","lindt":"30.88","nestle":"18.43","other":"12.90"},"oughts":{"hershey":"38.12","mars":"11.66","lindt":"31.39","nestle":"8.97","other":"9.87"}}},{"name":"Arkansas","candy":{"seventies":{"hershey":"31.29","mars":"34.17","lindt":"3.60","nestle":"25.54","other":"5.40"},"eighties":{"hershey":"15.70","mars":"40.50","lindt":"11.98","nestle":"24.79","other":"7.02"},"ninties":{"hershey":"45.05","mars":"14.84","lindt":"24.18","nestle":"14.84","other":"1.10"},"oughts":{"hershey":"32.37","mars":"27.80","lindt":"31.54","nestle":"4.15","other":"4.15"}}},{"name":"California","candy":{"seventies":{"hershey":"7.83","mars":"31.34","lindt":"27.65","nestle":"20.28","other":"12.90"},"eighties":{"hershey":"2.81","mars":"24.10","lindt":"26.10","nestle":"36.55","other":"10.44"},"ninties":{"hershey":"50.82","mars":"9.84","lindt":"29.51","nestle":"4.92","other":"4.92"},"oughts":{"hershey":"22.48","mars":"32.55","lindt":"30.20","nestle":"14.09","other":"0.67"}}},{"name":"Colorado","candy":{"seventies":{"hershey":"27.71","mars":"22.89","lindt":"6.63","nestle":"30.12","other":"12.65"},"eighties":{"hershey":"12.43","mars":"42.60","lindt":"20.12","nestle":"6.51","other":"18.34"},"ninties":{"hershey":"22.29","mars":"28.61","lindt":"24.40","nestle":"17.47","other":"7.23"},"oughts":{"hershey":"32.37","mars":"14.45","lindt":"42.20","nestle":"8.67","other":"2.31"}}},{"name":"Connecticut","candy":{"seventies":{"hershey":"44.50","mars":"0.52","lindt":"15.18","nestle":"32.46","other":"7.33"},"eighties":{"hershey":"24.08","mars":"27.76","lindt":"21.40","nestle":"19.40","other":"7.36"},"ninties":{"hershey":"47.50","mars":"25.63","lindt":"8.13","nestle":"15.63","other":"3.13"},"oughts":{"hershey":"20.20","mars":"9.09","lindt":"33.00","nestle":"33.67","other":"4.04"}}},{"name":"Delaware","candy":{"seventies":{"hershey":"33.33","mars":"18.72","lindt":"23.74","nestle":"10.96","other":"13.24"},"eighties":{"hershey":"14.41","mars":"37.12","lindt":"18.78","nestle":"15.28","other":"14.41"},"ninties":{"hershey":"22.13","mars":"11.91","lindt":"34.47","nestle":"27.66","other":"3.83"},"oughts":{"hershey":"63.89","mars":"18.06","lindt":"1.39","nestle":"6.25","other":"10.42"}}},{"name":"District Of Columbia","candy":{"seventies":{"hershey":"12.31","mars":"37.31","lindt":"4.48","nestle":"36.57","other":"9.33"},"eighties":{"hershey":"29.14","mars":"16.23","lindt":"26.82","nestle":"27.81","other":"0.00"},"ninties":{"hershey":"5.86","mars":"38.67","lindt":"26.56","nestle":"25.39","other":"3.52"},"oughts":{"hershey":"26.86","mars":"24.38","lindt":"16.53","nestle":"28.93","other":"3.31"}}},{"name":"Florida","candy":{"seventies":{"hershey":"5.61","mars":"34.11","lindt":"27.10","nestle":"30.84","other":"2.34"},"eighties":{"hershey":"29.89","mars":"11.11","lindt":"19.92","nestle":"28.74","other":"10.34"},"ninties":{"hershey":"25.72","mars":"10.14","lindt":"34.42","nestle":"17.75","other":"11.96"},"oughts":{"hershey":"26.50","mars":"17.00","lindt":"32.50","nestle":"17.50","other":"6.50"}}},{"name":"Georgia","candy":{"seventies":{"hershey":"26.81","mars":"12.32","lindt":"25.72","nestle":"28.26","other":"6.88"},"eighties":{"hershey":"39.82","mars":"13.12","lindt":"9.95","nestle":"36.65","other":"0.45"},"ninties":{"hershey":"39.13","mars":"9.18","lindt":"5.31","nestle":"36.71","other":"9.66"},"oughts":{"hershey":"24.29","mars":"1.43","lindt":"20.00","nestle":"41.43","other":"12.86"}}},{"name":"Hawaii","candy":{"seventies":{"hershey":"7.10","mars":"38.25","lindt":"23.50","nestle":"28.96","other":"2.19"},"eighties":{"hershey":"16.76","mars":"47.57","lindt":"21.08","nestle":"3.24","other":"11.35"},"ninties":{"hershey":"32.67","mars":"26.29","lindt":"19.12","nestle":"9.56","other":"12.35"},"oughts":{"hershey":"40.20","mars":"7.84","lindt":"18.63","nestle":"32.35","other":"0.98"}}},{"name":"Idaho","candy":{"seventies":{"hershey":"32.14","mars":"39.80","lindt":"2.55","nestle":"11.73","other":"13.78"},"eighties":{"hershey":"4.72","mars":"30.66","lindt":"21.23","nestle":"31.60","other":"11.79"},"ninties":{"hershey":"15.22","mars":"20.29","lindt":"55.07","nestle":"1.45","other":"7.97"},"oughts":{"hershey":"29.02","mars":"28.32","lindt":"11.89","nestle":"30.07","other":"0.70"}}},{"name":"Illinois","candy":{"seventies":{"hershey":"25.26","mars":"12.29","lindt":"22.87","nestle":"34.13","other":"5.46"},"eighties":{"hershey":"33.06","mars":"20.66","lindt":"28.93","nestle":"9.92","other":"7.44"},"ninties":{"hershey":"26.80","mars":"22.68","lindt":"20.96","nestle":"23.37","other":"6.19"},"oughts":{"hershey":"43.60","mars":"27.49","lindt":"3.79","nestle":"19.43","other":"5.69"}}},{"name":"Indiana","candy":{"seventies":{"hershey":"10.83","mars":"38.22","lindt":"1.27","nestle":"31.21","other":"18.47"},"eighties":{"hershey":"22.69","mars":"23.11","lindt":"12.18","nestle":"28.57","other":"13.45"},"ninties":{"hershey":"41.01","mars":"12.90","lindt":"31.34","nestle":"9.22","other":"5.53"},"oughts":{"hershey":"21.92","mars":"18.26","lindt":"26.48","nestle":"29.68","other":"3.65"}}},{"name":"Iowa","candy":{"seventies":{"hershey":"22.05","mars":"22.43","lindt":"36.88","nestle":"7.22","other":"11.41"},"eighties":{"hershey":"34.51","mars":"8.24","lindt":"16.47","nestle":"35.29","other":"5.49"},"ninties":{"hershey":"25.27","mars":"21.43","lindt":"2.75","nestle":"39.56","other":"10.99"},"oughts":{"hershey":"25.91","mars":"6.36","lindt":"38.64","nestle":"20.00","other":"9.09"}}},{"name":"Kansas","candy":{"seventies":{"hershey":"16.67","mars":"6.94","lindt":"5.56","nestle":"67.36","other":"3.47"},"eighties":{"hershey":"34.18","mars":"20.36","lindt":"22.55","nestle":"14.91","other":"8.00"},"ninties":{"hershey":"29.32","mars":"1.13","lindt":"28.95","nestle":"31.20","other":"9.40"},"oughts":{"hershey":"31.52","mars":"32.12","lindt":"25.45","nestle":"3.64","other":"7.27"}}},{"name":"Kentucky","candy":{"seventies":{"hershey":"0.40","mars":"33.33","lindt":"30.52","nestle":"25.30","other":"10.44"},"eighties":{"hershey":"14.38","mars":"26.09","lindt":"25.08","nestle":"27.76","other":"6.69"},"ninties":{"hershey":"33.62","mars":"17.47","lindt":"11.35","nestle":"30.57","other":"6.99"},"oughts":{"hershey":"2.73","mars":"32.81","lindt":"33.59","nestle":"24.61","other":"6.25"}}},{"name":"Louisiana","candy":{"seventies":{"hershey":"9.41","mars":"39.60","lindt":"34.16","nestle":"10.89","other":"5.94"},"eighties":{"hershey":"20.85","mars":"24.43","lindt":"31.92","nestle":"14.98","other":"7.82"},"ninties":{"hershey":"27.76","mars":"27.40","lindt":"12.81","nestle":"20.28","other":"11.74"},"oughts":{"hershey":"7.39","mars":"23.74","lindt":"23.74","nestle":"38.52","other":"6.61"}}},{"name":"Maine","candy":{"seventies":{"hershey":"4.31","mars":"15.52","lindt":"34.91","nestle":"33.62","other":"11.64"},"eighties":{"hershey":"6.49","mars":"37.30","lindt":"34.59","nestle":"19.46","other":"2.16"},"ninties":{"hershey":"32.68","mars":"45.37","lindt":"17.56","nestle":"2.44","other":"1.95"},"oughts":{"hershey":"16.55","mars":"35.97","lindt":"7.19","nestle":"35.25","other":"5.04"}}},{"name":"Maryland","candy":{"seventies":{"hershey":"34.27","mars":"6.10","lindt":"44.13","nestle":"15.02","other":"0.47"},"eighties":{"hershey":"9.26","mars":"33.70","lindt":"30.74","nestle":"17.41","other":"8.89"},"ninties":{"hershey":"12.26","mars":"50.97","lindt":"5.16","nestle":"28.39","other":"3.23"},"oughts":{"hershey":"25.63","mars":"13.29","lindt":"24.05","nestle":"30.38","other":"6.65"}}},{"name":"Massachusetts","candy":{"seventies":{"hershey":"9.68","mars":"14.75","lindt":"26.73","nestle":"35.94","other":"12.90"},"eighties":{"hershey":"12.60","mars":"9.06","lindt":"25.98","nestle":"39.37","other":"12.99"},"ninties":{"hershey":"18.49","mars":"16.60","lindt":"23.40","nestle":"32.08","other":"9.43"},"oughts":{"hershey":"44.08","mars":"23.22","lindt":"13.74","nestle":"9.48","other":"9.48"}}},{"name":"Michigan","candy":{"seventies":{"hershey":"61.88","mars":"13.13","lindt":"17.50","nestle":"3.13","other":"4.38"},"eighties":{"hershey":"25.51","mars":"29.25","lindt":"22.79","nestle":"15.31","other":"7.14"},"ninties":{"hershey":"26.59","mars":"14.45","lindt":"16.18","nestle":"39.88","other":"2.89"},"oughts":{"hershey":"24.02","mars":"41.48","lindt":"13.10","nestle":"10.04","other":"11.35"}}},{"name":"Minnesota","candy":{"seventies":{"hershey":"13.48","mars":"43.26","lindt":"14.89","nestle":"11.35","other":"17.02"},"eighties":{"hershey":"16.67","mars":"35.19","lindt":"28.15","nestle":"15.56","other":"4.44"},"ninties":{"hershey":"10.83","mars":"24.58","lindt":"28.75","nestle":"23.75","other":"12.08"},"oughts":{"hershey":"18.45","mars":"19.42","lindt":"1.94","nestle":"48.06","other":"12.14"}}},{"name":"Mississippi","candy":{"seventies":{"hershey":"40.00","mars":"33.14","lindt":"5.71","nestle":"15.43","other":"5.71"},"eighties":{"hershey":"20.36","mars":"23.08","lindt":"2.71","nestle":"39.82","other":"14.03"},"ninties":{"hershey":"36.26","mars":"6.59","lindt":"16.48","nestle":"30.77","other":"9.89"},"oughts":{"hershey":"57.72","mars":"1.34","lindt":"7.38","nestle":"12.75","other":"20.81"}}},{"name":"Missouri","candy":{"seventies":{"hershey":"24.65","mars":"31.60","lindt":"31.25","nestle":"7.64","other":"4.86"},"eighties":{"hershey":"26.99","mars":"34.26","lindt":"33.22","nestle":"0.35","other":"5.19"},"ninties":{"hershey":"48.54","mars":"9.71","lindt":"23.79","nestle":"4.85","other":"13.11"},"oughts":{"hershey":"15.53","mars":"0.62","lindt":"29.81","nestle":"46.58","other":"7.45"}}},{"name":"Montana","candy":{"seventies":{"hershey":"28.82","mars":"2.62","lindt":"41.48","nestle":"15.72","other":"11.35"},"eighties":{"hershey":"9.70","mars":"39.39","lindt":"29.70","nestle":"3.64","other":"17.58"},"ninties":{"hershey":"16.93","mars":"33.07","lindt":"24.80","nestle":"17.72","other":"7.48"},"oughts":{"hershey":"30.47","mars":"15.02","lindt":"18.45","nestle":"30.90","other":"5.15"}}},{"name":"Nebraska","candy":{"seventies":{"hershey":"25.47","mars":"6.21","lindt":"14.91","nestle":"44.10","other":"9.32"},"eighties":{"hershey":"11.49","mars":"36.60","lindt":"14.89","nestle":"34.47","other":"2.55"},"ninties":{"hershey":"18.70","mars":"22.17","lindt":"15.65","nestle":"37.39","other":"6.09"},"oughts":{"hershey":"6.06","mars":"11.52","lindt":"27.88","nestle":"47.27","other":"7.27"}}},{"name":"Nevada","candy":{"seventies":{"hershey":"20.47","mars":"33.92","lindt":"13.45","nestle":"26.32","other":"5.85"},"eighties":{"hershey":"7.25","mars":"29.39","lindt":"16.79","nestle":"34.35","other":"12.21"},"ninties":{"hershey":"24.47","mars":"6.38","lindt":"27.30","nestle":"34.04","other":"7.80"},"oughts":{"hershey":"45.05","mars":"9.91","lindt":"12.16","nestle":"28.38","other":"4.50"}}},{"name":"New Hampshire","candy":{"seventies":{"hershey":"20.63","mars":"15.70","lindt":"37.67","nestle":"18.83","other":"7.17"},"eighties":{"hershey":"36.77","mars":"4.93","lindt":"27.80","nestle":"24.66","other":"5.83"},"ninties":{"hershey":"14.03","mars":"22.62","lindt":"24.43","nestle":"30.77","other":"8.14"},"oughts":{"hershey":"39.84","mars":"30.28","lindt":"14.74","nestle":"10.36","other":"4.78"}}},{"name":"New Jersey","candy":{"seventies":{"hershey":"14.29","mars":"59.18","lindt":"7.48","nestle":"19.05","other":"0.00"},"eighties":{"hershey":"17.22","mars":"36.26","lindt":"24.91","nestle":"13.92","other":"7.69"},"ninties":{"hershey":"13.13","mars":"24.06","lindt":"30.00","nestle":"23.75","other":"9.06"},"oughts":{"hershey":"52.11","mars":"26.76","lindt":"5.63","nestle":"2.11","other":"13.38"}}},{"name":"New Mexico","candy":{"seventies":{"hershey":"26.64","mars":"4.67","lindt":"25.23","nestle":"33.18","other":"10.28"},"eighties":{"hershey":"34.53","mars":"10.31","lindt":"8.52","nestle":"38.12","other":"8.52"},"ninties":{"hershey":"28.98","mars":"24.08","lindt":"36.33","nestle":"1.22","other":"9.39"},"oughts":{"hershey":"2.95","mars":"14.77","lindt":"40.93","nestle":"32.07","other":"9.28"}}},{"name":"New York","candy":{"seventies":{"hershey":"41.15","mars":"5.73","lindt":"6.77","nestle":"42.71","other":"3.65"},"eighties":{"hershey":"7.05","mars":"27.88","lindt":"26.60","nestle":"28.85","other":"9.62"},"ninties":{"hershey":"24.17","mars":"15.00","lindt":"40.42","nestle":"8.75","other":"11.67"},"oughts":{"hershey":"42.34","mars":"12.41","lindt":"27.01","nestle":"7.30","other":"10.95"}}},{"name":"North Carolina","candy":{"seventies":{"hershey":"32.79","mars":"1.23","lindt":"21.72","nestle":"36.89","other":"7.38"},"eighties":{"hershey":"2.01","mars":"4.03","lindt":"32.89","nestle":"46.98","other":"14.09"},"ninties":{"hershey":"5.66","mars":"49.06","lindt":"16.04","nestle":"20.75","other":"8.49"},"oughts":{"hershey":"22.22","mars":"32.44","lindt":"20.44","nestle":"17.33","other":"7.56"}}},{"name":"North Dakota","candy":{"seventies":{"hershey":"35.51","mars":"31.31","lindt":"17.76","nestle":"10.28","other":"5.14"},"eighties":{"hershey":"18.64","mars":"25.42","lindt":"0.85","nestle":"50.85","other":"4.24"},"ninties":{"hershey":"16.03","mars":"28.57","lindt":"22.16","nestle":"23.91","other":"9.33"},"oughts":{"hershey":"0.39","mars":"31.64","lindt":"25.78","nestle":"36.33","other":"5.86"}}},{"name":"Ohio","candy":{"seventies":{"hershey":"32.34","mars":"23.35","lindt":"11.98","nestle":"22.16","other":"10.18"},"eighties":{"hershey":"36.70","mars":"28.46","lindt":"28.09","nestle":"5.62","other":"1.12"},"ninties":{"hershey":"12.40","mars":"44.63","lindt":"1.65","nestle":"14.05","other":"27.27"},"oughts":{"hershey":"12.97","mars":"8.65","lindt":"38.38","nestle":"31.89","other":"8.11"}}},{"name":"Oklahoma","candy":{"seventies":{"hershey":"27.48","mars":"18.87","lindt":"32.45","nestle":"13.25","other":"7.95"},"eighties":{"hershey":"39.24","mars":"16.03","lindt":"31.65","nestle":"2.95","other":"10.13"},"ninties":{"hershey":"6.80","mars":"48.98","lindt":"17.01","nestle":"16.33","other":"10.88"},"oughts":{"hershey":"2.92","mars":"59.12","lindt":"9.49","nestle":"8.76","other":"19.71"}}},{"name":"Oregon","candy":{"seventies":{"hershey":"31.67","mars":"55.56","lindt":"5.00","nestle":"5.56","other":"2.22"},"eighties":{"hershey":"2.54","mars":"17.39","lindt":"35.87","nestle":"35.14","other":"9.06"},"ninties":{"hershey":"20.95","mars":"33.99","lindt":"1.58","nestle":"37.94","other":"5.53"},"oughts":{"hershey":"5.00","mars":"43.00","lindt":"22.00","nestle":"20.00","other":"10.00"}}},{"name":"Pennsylvania","candy":{"seventies":{"hershey":"44.29","mars":"34.25","lindt":"8.68","nestle":"2.28","other":"10.50"},"eighties":{"hershey":"12.10","mars":"26.21","lindt":"38.31","nestle":"18.95","other":"4.44"},"ninties":{"hershey":"52.38","mars":"24.87","lindt":"10.58","nestle":"5.82","other":"6.35"},"oughts":{"hershey":"35.40","mars":"9.73","lindt":"41.59","nestle":"6.19","other":"7.08"}}},{"name":"Rhode Island","candy":{"seventies":{"hershey":"18.52","mars":"32.22","lindt":"32.59","nestle":"10.74","other":"5.93"},"eighties":{"hershey":"25.00","mars":"35.77","lindt":"18.46","nestle":"12.69","other":"8.08"},"ninties":{"hershey":"18.15","mars":"24.32","lindt":"10.81","nestle":"34.36","other":"12.36"},"oughts":{"hershey":"30.93","mars":"10.31","lindt":"3.61","nestle":"44.33","other":"10.82"}}},{"name":"South Carolina","candy":{"seventies":{"hershey":"14.23","mars":"28.87","lindt":"35.98","nestle":"9.21","other":"11.72"},"eighties":{"hershey":"40.70","mars":"26.74","lindt":"16.28","nestle":"13.37","other":"2.91"},"ninties":{"hershey":"48.12","mars":"21.05","lindt":"0.75","nestle":"30.08","other":"0.00"},"oughts":{"hershey":"9.33","mars":"37.82","lindt":"41.97","nestle":"5.70","other":"5.18"}}},{"name":"South Dakota","candy":{"seventies":{"hershey":"27.12","mars":"33.90","lindt":"20.34","nestle":"11.86","other":"6.78"},"eighties":{"hershey":"32.62","mars":"24.46","lindt":"1.29","nestle":"31.76","other":"9.87"},"ninties":{"hershey":"24.76","mars":"25.08","lindt":"9.45","nestle":"32.25","other":"8.47"},"oughts":{"hershey":"1.63","mars":"39.59","lindt":"30.61","nestle":"15.10","other":"13.06"}}},{"name":"Tennessee","candy":{"seventies":{"hershey":"23.94","mars":"25.07","lindt":"17.75","nestle":"24.79","other":"8.45"},"eighties":{"hershey":"14.72","mars":"31.60","lindt":"36.36","nestle":"7.79","other":"9.52"},"ninties":{"hershey":"18.09","mars":"32.42","lindt":"28.33","nestle":"11.26","other":"9.90"},"oughts":{"hershey":"21.46","mars":"42.44","lindt":"17.56","nestle":"15.12","other":"3.41"}}},{"name":"Texas","candy":{"seventies":{"hershey":"20.92","mars":"26.78","lindt":"20.50","nestle":"29.71","other":"2.09"},"eighties":{"hershey":"27.82","mars":"37.90","lindt":"10.89","nestle":"14.11","other":"9.27"},"ninties":{"hershey":"21.50","mars":"30.62","lindt":"27.69","nestle":"20.20","other":"0.00"},"oughts":{"hershey":"20.93","mars":"21.51","lindt":"35.47","nestle":"19.77","other":"2.33"}}},{"name":"Utah","candy":{"seventies":{"hershey":"1.44","mars":"38.46","lindt":"30.77","nestle":"16.83","other":"12.50"},"eighties":{"hershey":"35.68","mars":"6.49","lindt":"11.89","nestle":"38.92","other":"7.03"},"ninties":{"hershey":"22.22","mars":"1.65","lindt":"34.98","nestle":"35.80","other":"5.35"},"oughts":{"hershey":"11.06","mars":"12.56","lindt":"32.66","nestle":"43.22","other":"0.50"}}},{"name":"Vermont","candy":{"seventies":{"hershey":"17.31","mars":"0.96","lindt":"55.77","nestle":"19.23","other":"6.73"},"eighties":{"hershey":"28.57","mars":"19.48","lindt":"15.58","nestle":"9.09","other":"27.27"},"ninties":{"hershey":"22.84","mars":"9.34","lindt":"25.61","nestle":"33.91","other":"8.30"},"oughts":{"hershey":"29.12","mars":"27.59","lindt":"22.61","nestle":"10.34","other":"10.34"}}},{"name":"Virginia","candy":{"seventies":{"hershey":"44.33","mars":"5.15","lindt":"6.19","nestle":"43.30","other":"1.03"},"eighties":{"hershey":"10.31","mars":"25.95","lindt":"29.39","nestle":"25.95","other":"8.40"},"ninties":{"hershey":"33.11","mars":"37.16","lindt":"7.43","nestle":"14.19","other":"8.11"},"oughts":{"hershey":"29.63","mars":"37.04","lindt":"4.44","nestle":"25.19","other":"3.70"}}},{"name":"Washington","candy":{"seventies":{"hershey":"21.74","mars":"28.76","lindt":"22.41","nestle":"24.41","other":"2.68"},"eighties":{"hershey":"19.64","mars":"2.38","lindt":"42.26","nestle":"35.71","other":"0.00"},"ninties":{"hershey":"51.43","mars":"6.86","lindt":"11.43","nestle":"18.86","other":"11.43"},"oughts":{"hershey":"10.87","mars":"27.72","lindt":"35.87","nestle":"13.04","other":"12.50"}}},{"name":"West Virginia","candy":{"seventies":{"hershey":"30.94","mars":"27.81","lindt":"6.88","nestle":"28.75","other":"5.63"},"eighties":{"hershey":"9.38","mars":"20.49","lindt":"28.82","nestle":"33.33","other":"7.99"},"ninties":{"hershey":"11.27","mars":"30.52","lindt":"37.56","nestle":"5.63","other":"15.02"},"oughts":{"hershey":"25.34","mars":"22.37","lindt":"25.61","nestle":"25.34","other":"1.35"}}},{"name":"Wisconsin","candy":{"seventies":{"hershey":"38.35","mars":"16.02","lindt":"12.62","nestle":"32.52","other":"0.49"},"eighties":{"hershey":"0.99","mars":"15.27","lindt":"37.44","nestle":"32.51","other":"13.79"},"ninties":{"hershey":"19.77","mars":"15.50","lindt":"31.01","nestle":"23.26","other":"10.47"},"oughts":{"hershey":"2.82","mars":"33.80","lindt":"40.38","nestle":"15.02","other":"7.98"}}},{"name":"Wyoming","candy":{"seventies":{"hershey":"35.09","mars":"9.36","lindt":"33.92","nestle":"9.36","other":"12.28"},"eighties":{"hershey":"10.83","mars":"40.00","lindt":"39.17","nestle":"8.75","other":"1.25"},"ninties":{"hershey":"28.43","mars":"25.49","lindt":"22.22","nestle":"19.28","other":"4.58"},"oughts":{"hershey":"20.09","mars":"5.94","lindt":"25.57","nestle":"36.99","other":"11.42"}}}]